kazoo/__init__.py
kazoo/client.py
kazoo/exceptions.py
kazoo/request_objects.py
kazoo/rest_resources.py
kazoo_sdk-0.2.3.dist-info/DESCRIPTION.rst
kazoo_sdk-0.2.3.dist-info/METADATA
kazoo_sdk-0.2.3.dist-info/RECORD
kazoo_sdk-0.2.3.dist-info/WHEEL
kazoo_sdk-0.2.3.dist-info/metadata.json
kazoo_sdk-0.2.3.dist-info/top_level.txt
tasks/__init__.py
tasks/py.py
tasks/test.py
tests/__init__.py
tests/test_authentication.py
tests/test_client_metaclass.py
tests/test_initialization.py
tests/test_request_objects.py
tests/test_rest_method_objects.py
tests/utils.py
