Metadata-Version: 2.0
Name: kazoo-sdk
Version: 0.2.3
Summary: Wrapper for the Kazoo API
Home-page: https://github.com/telephoneorg/kazoo-sdk
Author: Alex Good, Updated by Brock Haywood, Refreshed by Joe Black
Author-email: me@joeblack.nyc
License: MIT License
Download-URL: https://github.com/telephoneorg/kazoo-sdk/tarball/v0.2.3
Platform: UNKNOWN
Classifier: Development Status :: 3 - Alpha
Classifier: Environment :: Other Environment
Classifier: Intended Audience :: Developers
Classifier: Intended Audience :: Telecommunications Industry
Classifier: Intended Audience :: System Administrators
Classifier: License :: OSI Approved :: MIT License
Classifier: Operating System :: OS Independent
Classifier: Programming Language :: Python
Classifier: Programming Language :: Python :: 2
Classifier: Programming Language :: Python :: 2.7
Classifier: Programming Language :: Python :: 3
Classifier: Programming Language :: Python :: 3.6
Classifier: Topic :: Communications :: Telephony
Classifier: Topic :: System :: Systems Administration
Classifier: Topic :: Utilities
Requires-Dist: requests (>=2.2.1)
Requires-Dist: six
